twisted/plugins/nusbot_plugin.py
nusbot-0.3.3.dist-info/METADATA
nusbot-0.3.3.dist-info/RECORD
nusbot-0.3.3.dist-info/metadata.json
nusbot-0.3.3.dist-info/top_level.txt
nusbot-0.3.3.dist-info/DESCRIPTION.rst
nusbot-0.3.3.dist-info/WHEEL
nusbot/__init__.py
nusbot/filelist.py
nusbot/adc.py
nusbot/protocol.py
nusbot/factory.py
nusbot/storage.py
