Metadata-Version: 2.0
Name: nusbot
Version: 0.3.3
Summary: adc bot annoucing changes in filelist of hub's users
Home-page: https://github.com/kraiz/nusbot
Author: Lars Kreisz
Author-email: lars.kreisz@gmail.com
License: MIT
Platform: UNKNOWN
Classifier: Development Status :: 3 - Alpha
Classifier: Intended Audience :: Information Technology
Classifier: Natural Language :: English
Classifier: License :: OSI Approved :: MIT License
Classifier: Operating System :: OS Independent
Classifier: Programming Language :: Python
Classifier: Programming Language :: Python :: 3.4
Classifier: Topic :: Communications :: Chat
Classifier: Topic :: Communications :: File Sharing
Requires-Dist: twisted
